{
  "details": {
    "intro": {
      "courseData": "background.sh",
      "title": "Install Aporeto Enforcerd on Kubernetes",
      "text": "intro.md"
    },
    "steps": [
      {
          "title": "Katacoda Setup",
          "text": "_setup.md"
      },
      {
        "title": "Deploy App Credentials",
        "text": "step2.md"
      },
      {
        "title": "Deploy Enforcerd",
        "text": "step3.md"
      },
      {
        "title": "Deploy a demo app",
        "text": "step4.md"
      }
    ],
    "assets": {
      "host01": [
          {
            "file": "common-setup-aporeto.sh",
            "target": "/opt/",
            "chmod": "+x"
          },
          {
            "file": "common-setup.sh",
            "target": "/opt/",
            "chmod": "+x"
          },
          {
            "file": "post-setup.sh",
            "target": "/opt/",
            "chmod": "+x"
          }
      ]
    }
  },
  "environment": {
    "hidefinish": true,
    "uilayout": "terminal"
  },
  "backend": {
    "imageid": "kubernetes"
  }
}
